CryptoBotSDK/__init__.py
CryptoBotSDK/cryptobot.py
CryptoBotSDK/types/AppStats.py
CryptoBotSDK/types/Balance.py
CryptoBotSDK/types/Check.py
CryptoBotSDK/types/Currencies.py
CryptoBotSDK/types/ExchangeRate.py
CryptoBotSDK/types/Invoice.py
CryptoBotSDK/types/Transfer.py
CryptoBotSDK/types/__init__.py
cryptobotsdk-1.1.0.dist-info/licenses/LICENSE
cryptobotsdk-1.1.0.dist-info/METADATA
cryptobotsdk-1.1.0.dist-info/WHEEL
cryptobotsdk-1.1.0.dist-info/top_level.txt
cryptobotsdk-1.1.0.dist-info/RECORD
