Metadata-Version: 2.4
Name: CryptoBotSDK
Version: 1.1.0
Summary: CrytoBot (@send) telegram sdk
Home-page: https://github.com/yumieiko/CryptoBotSDK
Author: Daniil Yumieiko
Author-email: r3s1zetv@gmail.com
Requires-Python: >=3.6
License-File: LICENSE
Requires-Dist: requests>=2.32.3
Dynamic: author
Dynamic: author-email
Dynamic: home-page
Dynamic: license-file
